{
  "units": [
    {
      "Base Unit Name": null,
      "Upgraded Name": ["guardian"],
      "Attack Effectiveness Order": [
        "medium",
        "unarmored",
        "light",
        "heavy",
        "fortified"
      ],
      "Attack Weakness": ["fortified"],
      "Defense Effectiveness Order": [
        "pierce",
        "normal",
        "siege",
        "chaos",
        "magic"
      ],
      "Defense Strength": ["pierce"],
      "Defense Weakness": ["magic"],
      "Abilities": null,
      "Ability Type": null,
      "Ability Description": null,
      "Name": "ent",
      "Builder": "nature",
      "Unit Tier": 1,
      "Gold Cost": 20,
      "Food Cost": 1,
      "Upgradeable": true,
      "Max Upgrade Gold Cost": 95,
      "Total Food Cost with Upgrade": 1,
      "Base Min Hit": 11,
      "Base Max Hit": 13,
      "Attack Speed": 1.4,
      "Attack Speed Class": "fast",
      "Range": 100,
      "Melee / Ranged": "melee",
      "Hit Points": 115,
      "Mana": 0,
      "Attack Type": "normal",
      "Defense Type": "heavy",
      "Attack Strength": "medium",
      "Has Aura": false,
      "Can Buff": false,
      "Can Debuff": false,
      "Can Splash": false,
      "Can Heal": false,
      "Can Stun": false,
      "Can Summon": false,
      "ID": "whWT5nS",
      "Builder ID": "9vSKJJf"
    },
    {
      "Base Unit Name": ["ent"],
      "Upgraded Name": null,
      "Attack Effectiveness Order": [
        "medium",
        "unarmored",
        "light",
        "heavy",
        "fortified"
      ],
      "Attack Weakness": ["fortified"],
      "Defense Effectiveness Order": [
        "pierce",
        "normal",
        "siege",
        "chaos",
        "magic"
      ],
      "Defense Strength": ["pierce"],
      "Defense Weakness": ["magic"],
      "Abilities": ["entangle"],
      "Ability Type": ["crowd control"],
      "Ability Description": [
        "Entangles a nearby enemy unit immobilizing it and dealing 10 damage per second. Lasts 4 seconds."
      ],
      "Name": "guardian",
      "Builder": "nature",
      "Unit Tier": 1,
      "Gold Cost": 95,
      "Food Cost": 0,
      "Upgradeable": false,
      "Max Upgrade Gold Cost": 0,
      "Total Food Cost with Upgrade": 0,
      "Base Min Hit": 53,
      "Base Max Hit": 64,
      "Attack Speed": 1.4,
      "Attack Speed Class": "fast",
      "Range": 100,
      "Melee / Ranged": "melee",
      "Hit Points": 665,
      "Mana": 20,
      "Attack Type": "normal",
      "Defense Type": "heavy",
      "Attack Strength": "medium",
      "Has Aura": false,
      "Can Buff": false,
      "Can Debuff": true,
      "Can Splash": false,
      "Can Heal": false,
      "Can Stun": false,
      "Can Summon": false,
      "ID": "2j09B2D",
      "Builder ID": "9vSKJJf"
    },
    {
      "Base Unit Name": null,
      "Upgraded Name": ["meliai"],
      "Attack Effectiveness Order": [
        "light",
        "unarmored",
        "medium",
        "heavy",
        "fortified"
      ],
      "Attack Weakness": ["fortified"],
      "Defense Effectiveness Order": [
        "magic",
        "pierce",
        "siege",
        "chaos",
        "normal"
      ],
      "Defense Strength": ["magic"],
      "Defense Weakness": ["normal"],
      "Abilities": ["vulture eye"],
      "Ability Type": ["damage"],
      "Ability Description": [
        "This unit has a 33% chance to do 160% damage. Affects air enemies only."
      ],
      "Name": "ranger",
      "Builder": "nature",
      "Unit Tier": 2,
      "Gold Cost": 40,
      "Food Cost": 1,
      "Upgradeable": true,
      "Max Upgrade Gold Cost": 115,
      "Total Food Cost with Upgrade": 1,
      "Base Min Hit": 15,
      "Base Max Hit": 18,
      "Attack Speed": 0.9,
      "Attack Speed Class": "very fast",
      "Range": 750,
      "Melee / Ranged": "ranged",
      "Hit Points": 110,
      "Mana": 0,
      "Attack Type": "pierce",
      "Defense Type": "medium",
      "Attack Strength": "light",
      "Has Aura": false,
      "Can Buff": false,
      "Can Debuff": false,
      "Can Splash": false,
      "Can Heal": false,
      "Can Stun": false,
      "Can Summon": false,
      "ID": "C18T9ah",
      "Builder ID": "9vSKJJf"
    },
    {
      "Base Unit Name": ["ranger"],
      "Upgraded Name": null,
      "Attack Effectiveness Order": [
        "light",
        "unarmored",
        "medium",
        "heavy",
        "fortified"
      ],
      "Attack Weakness": ["fortified"],
      "Defense Effectiveness Order": [
        "magic",
        "pierce",
        "siege",
        "chaos",
        "normal"
      ],
      "Defense Strength": ["magic"],
      "Defense Weakness": ["normal"],
      "Abilities": ["precision", "mark target"],
      "Ability Type": ["damage", "damage"],
      "Ability Description": [
        "This unit has a 33% chance to do 160% damage. Affects all enemies.",
        "Each attack marks an enemy target causing it to take 25% more damage from piercing attacks. Does not stack."
      ],
      "Name": "meliai",
      "Builder": "nature",
      "Unit Tier": 2,
      "Gold Cost": 115,
      "Food Cost": 0,
      "Upgradeable": false,
      "Max Upgrade Gold Cost": 0,
      "Total Food Cost with Upgrade": 0,
      "Base Min Hit": 40,
      "Base Max Hit": 43,
      "Attack Speed": 0.9,
      "Attack Speed Class": "very fast",
      "Range": 750,
      "Melee / Ranged": "ranged",
      "Hit Points": 335,
      "Mana": 0,
      "Attack Type": "pierce",
      "Defense Type": "medium",
      "Attack Strength": "light",
      "Has Aura": false,
      "Can Buff": false,
      "Can Debuff": false,
      "Can Splash": false,
      "Can Heal": false,
      "Can Stun": false,
      "Can Summon": false,
      "ID": "s9e44kN",
      "Builder ID": "9vSKJJf"
    },
    {
      "Base Unit Name": null,
      "Upgraded Name": ["thunderbird"],
      "Attack Effectiveness Order": [
        "heavy",
        "light",
        "unarmored",
        "medium",
        "fortifed"
      ],
      "Attack Weakness": ["fortified"],
      "Defense Effectiveness Order": [
        "normal",
        "siege",
        "chaos",
        "magic",
        "pierce"
      ],
      "Defense Strength": ["normal", "siege"],
      "Defense Weakness": ["pierce"],
      "Abilities": ["faerie luck"],
      "Ability Type": ["self buff"],
      "Ability Description": ["Gives a 15% chance to dodge an attack."],
      "Name": "sprite",
      "Builder": "nature",
      "Unit Tier": 3,
      "Gold Cost": 80,
      "Food Cost": 1,
      "Upgradeable": true,
      "Max Upgrade Gold Cost": 155,
      "Total Food Cost with Upgrade": 2,
      "Base Min Hit": 22,
      "Base Max Hit": 27,
      "Attack Speed": 0.66,
      "Attack Speed Class": "very fast",
      "Range": 300,
      "Melee / Ranged": "ranged",
      "Hit Points": 360,
      "Mana": 0,
      "Attack Type": "magic",
      "Defense Type": "light",
      "Attack Strength": "heavy",
      "Has Aura": false,
      "Can Buff": false,
      "Can Debuff": false,
      "Can Splash": false,
      "Can Heal": false,
      "Can Stun": false,
      "Can Summon": false,
      "ID": "FSP8lwd",
      "Builder ID": "9vSKJJf"
    },
    {
      "Base Unit Name": ["sprite"],
      "Upgraded Name": null,
      "Attack Effectiveness Order": [
        "heavy",
        "light",
        "unarmored",
        "medium",
        "fortifed"
      ],
      "Attack Weakness": ["fortified"],
      "Defense Effectiveness Order": [
        "pierce",
        "normal",
        "siege",
        "chaos",
        "magic"
      ],
      "Defense Strength": ["pierce"],
      "Defense Weakness": ["magic"],
      "Abilities": ["aftershock"],
      "Ability Type": ["splash"],
      "Ability Description": [
        "Shocks 2 nearby enemy for 45 magic damage with each attack."
      ],
      "Name": "thunderbird",
      "Builder": "nature",
      "Unit Tier": 3,
      "Gold Cost": 155,
      "Food Cost": 1,
      "Upgradeable": false,
      "Max Upgrade Gold Cost": 0,
      "Total Food Cost with Upgrade": 0,
      "Base Min Hit": 120,
      "Base Max Hit": 132,
      "Attack Speed": 1.8,
      "Attack Speed Class": "average",
      "Range": 300,
      "Melee / Ranged": "ranged",
      "Hit Points": 955,
      "Mana": 0,
      "Attack Type": "magic",
      "Defense Type": "heavy",
      "Attack Strength": "heavy",
      "Has Aura": false,
      "Can Buff": false,
      "Can Debuff": false,
      "Can Splash": true,
      "Can Heal": false,
      "Can Stun": false,
      "Can Summon": false,
      "ID": "G4tKjTR",
      "Builder ID": "9vSKJJf"
    },
    {
      "Base Unit Name": null,
      "Upgraded Name": ["tree of time"],
      "Attack Effectiveness Order": [
        "medium",
        "unarmored",
        "light",
        "heavy",
        "fortified"
      ],
      "Attack Weakness": ["fortified"],
      "Defense Effectiveness Order": [
        "magic",
        "pierce",
        "siege",
        "chaos",
        "normal"
      ],
      "Defense Strength": ["magic"],
      "Defense Weakness": ["normal"],
      "Abilities": ["helping hand"],
      "Ability Type": ["aura - speed"],
      "Ability Description": ["Increases nearby allies' movement by 30%."],
      "Name": "tree of travel",
      "Builder": "nature",
      "Unit Tier": 4,
      "Gold Cost": 130,
      "Food Cost": 1,
      "Upgradeable": true,
      "Max Upgrade Gold Cost": 165,
      "Total Food Cost with Upgrade": 2,
      "Base Min Hit": 74,
      "Base Max Hit": 82,
      "Attack Speed": 1.5,
      "Attack Speed Class": "average",
      "Range": 100,
      "Melee / Ranged": "melee",
      "Hit Points": 750,
      "Mana": 0,
      "Attack Type": "normal",
      "Defense Type": "medium",
      "Attack Strength": "medium",
      "Has Aura": true,
      "Can Buff": true,
      "Can Debuff": false,
      "Can Splash": false,
      "Can Heal": false,
      "Can Stun": false,
      "Can Summon": false,
      "ID": "yxkmGck",
      "Builder ID": "9vSKJJf"
    },
    {
      "Base Unit Name": ["tree of travel"],
      "Upgraded Name": null,
      "Attack Effectiveness Order": [
        "medium",
        "unarmored",
        "light",
        "heavy",
        "fortified"
      ],
      "Attack Weakness": ["fortified"],
      "Defense Effectiveness Order": [
        "magic",
        "pierce",
        "siege",
        "chaos",
        "normal"
      ],
      "Defense Strength": ["magic"],
      "Defense Weakness": ["normal"],
      "Abilities": ["chrono trigger"],
      "Ability Type": ["aura - slow"],
      "Ability Description": ["Slows nearby enemies' movement by 50%."],
      "Name": "tree of time",
      "Builder": "nature",
      "Unit Tier": 4,
      "Gold Cost": 165,
      "Food Cost": 1,
      "Upgradeable": false,
      "Max Upgrade Gold Cost": 0,
      "Total Food Cost with Upgrade": 0,
      "Base Min Hit": 138,
      "Base Max Hit": 144,
      "Attack Speed": 1.5,
      "Attack Speed Class": "average",
      "Range": 100,
      "Melee / Ranged": "melee",
      "Hit Points": 1395,
      "Mana": 0,
      "Attack Type": "normal",
      "Defense Type": "medium",
      "Attack Strength": "medium",
      "Has Aura": true,
      "Can Buff": false,
      "Can Debuff": true,
      "Can Splash": false,
      "Can Heal": false,
      "Can Stun": false,
      "Can Summon": false,
      "ID": "YHuf4sa",
      "Builder ID": "9vSKJJf"
    },
    {
      "Base Unit Name": null,
      "Upgraded Name": ["goliath"],
      "Attack Effectiveness Order": [
        "medium",
        "unarmored",
        "light",
        "heavy",
        "fortified"
      ],
      "Attack Weakness": ["fortified"],
      "Defense Effectiveness Order": [
        "pierce",
        "normal",
        "siege",
        "chaos",
        "magic"
      ],
      "Defense Strength": ["pierce"],
      "Defense Weakness": ["magic"],
      "Abilities": null,
      "Ability Type": null,
      "Ability Description": null,
      "Name": "halfbreed",
      "Builder": "nature",
      "Unit Tier": 5,
      "Gold Cost": 195,
      "Food Cost": 1,
      "Upgradeable": true,
      "Max Upgrade Gold Cost": 225,
      "Total Food Cost with Upgrade": 3,
      "Base Min Hit": 86,
      "Base Max Hit": 90,
      "Attack Speed": 0.9,
      "Attack Speed Class": "very fast",
      "Range": 100,
      "Melee / Ranged": "melee",
      "Hit Points": 1005,
      "Mana": 0,
      "Attack Type": "normal",
      "Defense Type": "heavy",
      "Attack Strength": "medium",
      "Has Aura": false,
      "Can Buff": false,
      "Can Debuff": false,
      "Can Splash": false,
      "Can Heal": false,
      "Can Stun": false,
      "Can Summon": false,
      "ID": "Lqregxn",
      "Builder ID": "9vSKJJf"
    },
    {
      "Base Unit Name": ["halfbreed"],
      "Upgraded Name": null,
      "Attack Effectiveness Order": [
        "fortified",
        "unarmored",
        "light",
        "medium",
        "heavy"
      ],
      "Attack Weakness": ["light", "medium", "heavy"],
      "Defense Effectiveness Order": [
        "pierce",
        "normal",
        "siege",
        "chaos",
        "magic"
      ],
      "Defense Strength": ["pierce"],
      "Defense Weakness": ["magic"],
      "Abilities": ["natural armor", "reassurance"],
      "Ability Type": ["self buff", "aura - armor"],
      "Ability Description": [
        "30% Chance to reduce damage taken by 50 every time this unit is attacked. If the attack deals less than 50 damage it will deal 5 damage.",
        "Gives 3 additional armor to friendly units close to him. Very small area of effect."
      ],
      "Name": "goliath",
      "Builder": "nature",
      "Unit Tier": 5,
      "Gold Cost": 225,
      "Food Cost": 2,
      "Upgradeable": false,
      "Max Upgrade Gold Cost": 0,
      "Total Food Cost with Upgrade": 0,
      "Base Min Hit": 246,
      "Base Max Hit": 278,
      "Attack Speed": 1.8,
      "Attack Speed Class": "average",
      "Range": 180,
      "Melee / Ranged": "melee",
      "Hit Points": 1655,
      "Mana": 0,
      "Attack Type": "siege",
      "Defense Type": "heavy",
      "Attack Strength": "fortified",
      "Has Aura": true,
      "Can Buff": true,
      "Can Debuff": false,
      "Can Splash": false,
      "Can Heal": false,
      "Can Stun": false,
      "Can Summon": false,
      "ID": "VcPHwL2",
      "Builder ID": "9vSKJJf"
    },
    {
      "Base Unit Name": null,
      "Upgraded Name": ["tree of life", "tree of knowledge"],
      "Attack Effectiveness Order": [
        "heavy",
        "light",
        "unarmored",
        "medium",
        "fortifed"
      ],
      "Attack Weakness": ["fortified"],
      "Defense Effectiveness Order": [
        "pierce",
        "magic",
        "normal",
        "chaos",
        "siege"
      ],
      "Defense Strength": ["pierce"],
      "Defense Weakness": ["siege"],
      "Abilities": ["sacred blessing"],
      "Ability Type": ["heal"],
      "Ability Description": [
        "Heals up to 4 nearby allies for 40hp every 5 seconds."
      ],
      "Name": "yggdrasil",
      "Builder": "nature",
      "Unit Tier": 6,
      "Gold Cost": 290,
      "Food Cost": 2,
      "Upgradeable": true,
      "Max Upgrade Gold Cost": 380,
      "Total Food Cost with Upgrade": 4,
      "Base Min Hit": 91,
      "Base Max Hit": 102,
      "Attack Speed": 0.8,
      "Attack Speed Class": "very fast",
      "Range": 180,
      "Melee / Ranged": "melee",
      "Hit Points": 1250,
      "Mana": 0,
      "Attack Type": "magic",
      "Defense Type": "fortified",
      "Attack Strength": "heavy",
      "Has Aura": false,
      "Can Buff": false,
      "Can Debuff": false,
      "Can Splash": false,
      "Can Heal": true,
      "Can Stun": false,
      "Can Summon": false,
      "ID": "KdK5XzM",
      "Builder ID": "9vSKJJf"
    },
    {
      "Base Unit Name": ["yggdrasil"],
      "Upgraded Name": null,
      "Attack Effectiveness Order": [
        "heavy",
        "light",
        "unarmored",
        "medium",
        "fortifed"
      ],
      "Attack Weakness": ["fortified"],
      "Defense Effectiveness Order": [
        "pierce",
        "magic",
        "normal",
        "chaos",
        "siege"
      ],
      "Defense Strength": ["pierce"],
      "Defense Weakness": ["siege"],
      "Abilities": ["water of life"],
      "Ability Type": ["heal"],
      "Ability Description": [
        "Heals up to 6 nearby allies for 40hp every 4 seconds. When this unit dies it heals up to 5 nearby allies for 150hp each."
      ],
      "Name": "tree of life",
      "Builder": "nature",
      "Unit Tier": 6,
      "Gold Cost": 380,
      "Food Cost": 2,
      "Upgradeable": false,
      "Max Upgrade Gold Cost": 0,
      "Total Food Cost with Upgrade": 0,
      "Base Min Hit": 301,
      "Base Max Hit": 334,
      "Attack Speed": 1.2,
      "Attack Speed Class": "fast",
      "Range": 180,
      "Melee / Ranged": "melee",
      "Hit Points": 2350,
      "Mana": 0,
      "Attack Type": "magic",
      "Defense Type": "fortified",
      "Attack Strength": "heavy",
      "Has Aura": false,
      "Can Buff": false,
      "Can Debuff": false,
      "Can Splash": false,
      "Can Heal": true,
      "Can Stun": false,
      "Can Summon": false,
      "ID": "0uEhfCI",
      "Builder ID": "9vSKJJf"
    },
    {
      "Base Unit Name": ["yggdrasil"],
      "Upgraded Name": null,
      "Attack Effectiveness Order": ["all"],
      "Attack Weakness": ["equal"],
      "Defense Effectiveness Order": [
        "pierce",
        "magic",
        "normal",
        "chaos",
        "siege"
      ],
      "Defense Strength": ["pierce"],
      "Defense Weakness": ["siege"],
      "Abilities": ["forbidden fruit"],
      "Ability Type": ["aura - reflect"],
      "Ability Description": [
        "Returns 24% of melee damage received back to attackers. Deals 200 damage to nearby enemies when it dies(limited to 15 target)."
      ],
      "Name": "tree of knowledge",
      "Builder": "nature",
      "Unit Tier": 6,
      "Gold Cost": 380,
      "Food Cost": 2,
      "Upgradeable": false,
      "Max Upgrade Gold Cost": 0,
      "Total Food Cost with Upgrade": 0,
      "Base Min Hit": 201,
      "Base Max Hit": 221,
      "Attack Speed": 1,
      "Attack Speed Class": "fast",
      "Range": 180,
      "Melee / Ranged": "melee",
      "Hit Points": 2570,
      "Mana": 0,
      "Attack Type": "chaos",
      "Defense Type": "fortified",
      "Attack Strength": "equal",
      "Has Aura": true,
      "Can Buff": false,
      "Can Debuff": true,
      "Can Splash": false,
      "Can Heal": false,
      "Can Stun": false,
      "Can Summon": false,
      "ID": "z76xsid",
      "Builder ID": "9vSKJJf"
    }
  ]
}
